ChangeLog
License
MANIFEST
MANIFEST.in
README
TODO
ez_setup.py
setup.py
src/Makefile
src/pdumpfs.py
src/PyDumpFS.egg-info/PKG-INFO
src/PyDumpFS.egg-info/SOURCES.txt
src/PyDumpFS.egg-info/dependency_links.txt
src/PyDumpFS.egg-info/top_level.txt
src/PyDumpFS.egg-info/zip-safe
src/pydumpfs/__init__.py
src/pydumpfs/locale/pdumpfs.pot
src/pydumpfs/locale/ja_JP/LC_MESSAGES/PyDumpFS.mo
src/pydumpfs/locale/ja_JP/LC_MESSAGES/PyDumpFS.po