Metadata-Version: 1.0
Name: PyDumpFS
Version: 1.0.8
Summary: Python base pseudo plan9's dump file system
Home-page: http://sourceforge.jp/projects/pydumpfs/
Author: MASA.H
Author-email: masahase@users.sourceforge.jp
License: New-style BSD License
Platform: Posix
Classifier: Development Status :: 5 - Production/Stable
Classifier: Environment :: Console
Classifier: Intended Audience :: End Users/Desktop
Classifier: Intended Audience :: System Administrators
Classifier: License :: OSI Approved :: BSD License
Classifier: Natural Language :: Japanese
Classifier: Operating System :: POSIX
Classifier: Programming Language :: Python
Classifier: Topic :: System :: Archiving :: Backup
